bdomarket/__init__.py
bdomarket/bdomarket.py
bdomarket/identifiers.py
bdomarket/response.py
bdomarket/utils.py
bdomarket-0.3.1.dist-info/METADATA
bdomarket-0.3.1.dist-info/WHEEL
bdomarket-0.3.1.dist-info/licenses/LICENSE
bdomarket-0.3.1.dist-info/RECORD
