Metadata-Version: 2.4
Name: bdomarket
Version: 0.3.1
Summary: API client for BDO market
License: GNU GENERAL PUBLIC LICENSE
License-File: LICENSE
Author: Szőke Dominik
Author-email: szokedominik@gmail.com
Requires-Python: >=3.1,<4.0
Classifier: Programming Language :: Python :: 3
Classifier: Topic :: Software Development :: Build Tools
Classifier: Topic :: Software Development :: Libraries :: Python Modules
Classifier: License :: OSI Approved :: GNU General Public License v3 (GPLv3)
Classifier: Operating System :: OS Independent
Provides-Extra: docs
Requires-Dist: aiohttp (>=3.12.14,<4.0.0)
Requires-Dist: asyncio (>=4.0.0,<5.0.0)
Requires-Dist: beautifulsoup4 (>=4.13.4,<5.0.0)
Requires-Dist: mkdocs (>=1.6.1,<2.0.0) ; extra == "docs"
Requires-Dist: mkdocstrings (>=0.30.0,<0.31.0)
Requires-Dist: mkdocstrings-python (>=1.16.12,<2.0.0)
Requires-Dist: mkdocstrings[python] (>=0.30.0,<1.0.0) ; extra == "docs"
Requires-Dist: pillow (>=12.0.0,<13.0.0)
Requires-Dist: requests (>=2.32.4,<3.0.0)
Requires-Dist: tqdm (>=4.67.1,<5.0.0)
Project-URL: Repository, https://github.com/Fizzor96/bdomarket
